gester/__init__.py
gester/example.gest
gester/example.mp3
gester/gest.py
gester-1.3.6.dist-info/entry_points.txt
gester-1.3.6.dist-info/LICENSE
gester-1.3.6.dist-info/METADATA
gester-1.3.6.dist-info/WHEEL
gester-1.3.6.dist-info/RECORD
