Metadata-Version: 2.1
Name: gester
Version: 1.3.6
Summary: A game engine for console based text game
Home-page: https://github.com/etcetra7n/gest
License: BSL-1.0
Keywords: games,game development,game engine,text-game-engine,console game engine
Author: John Anchery
Author-email: john.anchery@mail.ru
Requires-Python: >=3.0,<4.0
Classifier: License :: OSI Approved :: Boost Software License 1.0 (BSL-1.0)
Classifier: Operating System :: OS Independent
Classifier: Programming Language :: Python
Classifier: Programming Language :: Python :: 3
Classifier: Programming Language :: Python :: 3.4
Classifier: Programming Language :: Python :: 3.5
Classifier: Programming Language :: Python :: 3.6
Classifier: Programming Language :: Python :: 3.7
Classifier: Programming Language :: Python :: 3.8
Classifier: Programming Language :: Python :: 3.9
Classifier: Programming Language :: Python :: 3.10
Classifier: Programming Language :: Python :: 3.11
Classifier: Programming Language :: Python :: 3.12
Classifier: Programming Language :: Python :: 3.3
Classifier: Topic :: Games/Entertainment
Provides-Extra: pygame
Project-URL: Bug Tracker, https://github.com/etcetra7n/gest/issues
Project-URL: Repository, https://github.com/etcetra7n/gest
